nestifydict/__init__.py
nestifydict/nestifydict.py
nestifydict/test.py
nestifydict-0.0.9.dist-info/LICENSE
nestifydict-0.0.9.dist-info/METADATA
nestifydict-0.0.9.dist-info/WHEEL
nestifydict-0.0.9.dist-info/top_level.txt
nestifydict-0.0.9.dist-info/RECORD
