Metadata-Version: 2.1
Name: nestifydict
Version: 0.0.9
Summary: The purpose of this project is to provide an interface for nested dictionaries with unknown structures
Author-email: "Jared J. Beard" <jbeard6@mix.wvu.edu>
Project-URL: Homepage, https://github.com/jaredjbeard/nestifydict
Project-URL: Documentation, https://nestifydict.readthedocs.io/en/latest/
Classifier: Programming Language :: Python :: 3
Classifier: License :: OSI Approved :: BSD License
Classifier: Operating System :: OS Independent
Requires-Python: >=3.7
License-File: LICENSE
